{
  "29fb7d2a-eac2-4647-b19f-e9c7d45b225a": {
    "Carrello": [
      {
        "OrologioId": 5,
        "Orologio": {
          "Modello": "Daytona",
          "Referenza": "100100",
          "MaterialeId": 2,
          "Materiale": null,
          "TipologiaId": 1,
          "Tipologia": null,
          "Diametro": 0,
          "GenereId": 1,
          "Genere": null,
          "Prezzo": 25000.0,
          "Giacenza": 68,
          "Colore": "acciaio",
          "UrlImmagine": "https://www.bogliettigioielliere.com/wp-content/uploads/2024/07/m126500ln-0001_drp-upright-bba-with-shadow.png",
          "CategoriaId": 1,
          "Categoria": null,
          "MarcaId": 1,
          "Marca": null,
          "Id": 5,
          "Nome": "Rolex Daytona"
        },
        "QuantitaInCarrello": 1
      }
    ],
    "Totale": 25000.0,
    "Quantita": 1
  }
}